setup.cfg
setup.py
AndroidResR/AndroidResR.py
AndroidResR/__init__.py
AndroidResR.egg-info/PKG-INFO
AndroidResR.egg-info/SOURCES.txt
AndroidResR.egg-info/dependency_links.txt
AndroidResR.egg-info/entry_points.txt
AndroidResR.egg-info/top_level.txt
AndroidResR/util/ConfigLoader.py
AndroidResR/util/__init__.py
AndroidResR/view/AndroidResR.py
AndroidResR/view/__init__.py