Metadata-Version: 1.1
Name: AndroidResR
Version: 1.1.1
Summary: A resource manager for Android
Home-page: https://victorhqggqvsit.com
Author: Victor Häggqvist
Author-email: victor@hggqvst.com
License: GPLv2
Download-URL: https://github.com/victorhaggqvist/AndroidResR/tarball/1.0.1
Platform: UNKNOWN
